{
  "format_version": "1.13.0",
  "netease:block_geometry": {
    "bones": [
      {
        "cubes": [
          {
            "origin": [-16, -1, 8],
            "pivot": [-8, -1, 8],
            "rotation": [0, -45, 0],
            "size": [16, 16, 0],
            "uv": {
              "south": {
                "texture": 0,
                "uv": [0, 0],
                "uv_size": [16, 16]
              }
            }
          },
          {
            "origin": [-16, -1, 8],
            "pivot": [-8, -1, 8],
            "rotation": [0, -135, 0],
            "size": [16, 16, 0],
            "uv": {
              "south": {
                "texture": 0,
                "uv": [0, 0],
                "uv_size": [16, 16]
              }
            }
          }
        ],
        "name": "root",
        "pivot": [-8, -1, 8],
        "rotation": [0, 0, 0]
      },
      {
        "cubes": [
          {
            "origin": [-9, -1, 7],
            "pivot": [-7.5, 0, 7.5],
            "rotation": [0, 0, 0],
            "size": [2, 3, 2],
            "uv": {
              "down": {
                "texture": 3,
                "uv": [1, 0],
                "uv_size": [4, 4]
              },
              "east": {
                "texture": 3,
                "uv": [2, 0],
                "uv_size": [4, 6]
              },
              "north": {
                "texture": 3,
                "uv": [2, 0],
                "uv_size": [4, 6]
              },
              "south": {
                "texture": 3,
                "uv": [2, 0],
                "uv_size": [4, 6]
              },
              "up": {
                "texture": 3,
                "uv": [5, 4],
                "uv_size": [-4, -4]
              },
              "west": {
                "texture": 3,
                "uv": [2, 0],
                "uv_size": [4, 6]
              }
            }
          },
          {
            "origin": [-11.0, -1, 9.5],
            "pivot": [-10, 0, 10],
            "rotation": [0, 32.500000000000014, 0],
            "size": [1.5, 2, 1.5],
            "uv": {
              "down": {
                "texture": 3,
                "uv": [3, 0],
                "uv_size": [3, 3]
              },
              "east": {
                "texture": 3,
                "uv": [3, 0],
                "uv_size": [3, 4]
              },
              "north": {
                "texture": 3,
                "uv": [3, 0],
                "uv_size": [3, 4]
              },
              "south": {
                "texture": 3,
                "uv": [3, 0],
                "uv_size": [3, 4]
              },
              "up": {
                "texture": 3,
                "uv": [6, 3],
                "uv_size": [-3, -3]
              },
              "west": {
                "texture": 3,
                "uv": [3, 0],
                "uv_size": [3, 3]
              }
            }
          },
          {
            "origin": [-11.0, -1, 5],
            "pivot": [-10, 0, 5.5],
            "rotation": [0, 32.500000000000014, 0],
            "size": [1.5, 2, 1.5],
            "uv": {
              "down": {
                "texture": 3,
                "uv": [3, 0],
                "uv_size": [3, 3]
              },
              "east": {
                "texture": 3,
                "uv": [3, 0],
                "uv_size": [3, 4]
              },
              "north": {
                "texture": 3,
                "uv": [3, 0],
                "uv_size": [3, 4]
              },
              "south": {
                "texture": 3,
                "uv": [3, 0],
                "uv_size": [3, 4]
              },
              "up": {
                "texture": 3,
                "uv": [6, 3],
                "uv_size": [-3, -3]
              },
              "west": {
                "texture": 3,
                "uv": [3, 0],
                "uv_size": [3, 3]
              }
            }
          },
          {
            "origin": [-6.75, -1, 9.5],
            "pivot": [-5.75, 0, 10],
            "rotation": [0, 32.500000000000014, 0],
            "size": [1.5, 2, 1.5],
            "uv": {
              "down": {
                "texture": 3,
                "uv": [3, 0],
                "uv_size": [3, 3]
              },
              "east": {
                "texture": 3,
                "uv": [3, 0],
                "uv_size": [3, 4]
              },
              "north": {
                "texture": 3,
                "uv": [3, 0],
                "uv_size": [3, 4]
              },
              "south": {
                "texture": 3,
                "uv": [3, 0],
                "uv_size": [3, 4]
              },
              "up": {
                "texture": 3,
                "uv": [6, 3],
                "uv_size": [-3, -3]
              },
              "west": {
                "texture": 3,
                "uv": [3, 0],
                "uv_size": [3, 3]
              }
            }
          },
          {
            "origin": [-6.75, -1, 5],
            "pivot": [-5.75, 0, 5.5],
            "rotation": [0, 32.500000000000014, 0],
            "size": [1.5, 2, 1.5],
            "uv": {
              "down": {
                "texture": 3,
                "uv": [3, 0],
                "uv_size": [3, 3]
              },
              "east": {
                "texture": 3,
                "uv": [3, 0],
                "uv_size": [3, 4]
              },
              "north": {
                "texture": 3,
                "uv": [3, 0],
                "uv_size": [3, 4]
              },
              "south": {
                "texture": 3,
                "uv": [3, 0],
                "uv_size": [3, 4]
              },
              "up": {
                "texture": 3,
                "uv": [6, 3],
                "uv_size": [-3, -3]
              },
              "west": {
                "texture": 3,
                "uv": [3, 0],
                "uv_size": [3, 3]
              }
            }
          }
        ],
        "name": "fruit",
        "parent": "root",
        "pivot": [-8, -1, 8],
        "rotation": [0, 0, 0]
      },
      {
        "cubes": [
          {
            "origin": [
              -6.906688253644052, 7.915997960694601, 7.2909143272595704
            ],
            "pivot": [-6.146446609406726, 2.75, 6.681980515339465],
            "rotation": [
              -167.5000007008366, 72.50000082468232, 179.99999926515267
            ],
            "size": [2.5, 0.0, 3.000000000000008],
            "uv": {
              "up": {
                "texture": 1,
                "uv": [5, 6],
                "uv_size": [-5, -6]
              }
            }
          },
          {
            "origin": [
              -7.57784676902866, 2.044466597818502, 2.0545717526931355
            ],
            "pivot": [-3.83808784597353, 1.375, 6.404552841145755],
            "rotation": [
              -61.094232086737996, 73.71720429199011, -37.657829911405116
            ],
            "size": [4.499999999999998, 0.0, 5.499999999999998],
            "uv": {
              "up": {
                "texture": 2,
                "uv": [9, 11],
                "uv_size": [-9, -11]
              }
            }
          },
          {
            "origin": [
              -7.0860011887432215, 2.304000302070715, 1.4743305024180693
            ],
            "pivot": [-4.33808784597353, 0.625, 3.4045528411457546],
            "rotation": [
              148.22910913014667, -20.739922656404538, -173.35492174705877
            ],
            "size": [4.5, 0.0, 5.500000000000001],
            "uv": {
              "up": {
                "texture": 2,
                "uv": [9, 11],
                "uv_size": [-9, -11]
              }
            }
          },
          {
            "origin": [
              -5.467403224990573, 2.8750000000000018, 2.544192797772754
            ],
            "pivot": [
              -3.217403224990571, 2.8750000000000018, 5.294192797772757
            ],
            "rotation": [
              -48.35392936777095, 78.39259460422417, -18.926924319819133
            ],
            "size": [4.5, 0.0, 5.5000000000000036],
            "uv": {
              "up": {
                "texture": 2,
                "uv": [9, 11],
                "uv_size": [-9, -11]
              }
            }
          },
          {
            "origin": [
              -3.6638707861530153, 3.9571048471200667, -1.4920386453083192
            ],
            "pivot": [-4.33808784597353, 0.625, 3.4045528411457546],
            "rotation": [
              149.11836622205436, -13.288195707620924, -173.6156799378874
            ],
            "size": [4.499999999999994, 0.0, 5.499999999999998],
            "uv": {
              "up": {
                "texture": 2,
                "uv": [9, 11],
                "uv_size": [-9, -11]
              }
            }
          },
          {
            "origin": [
              -9.571803728816608, 8.05270594456329, 3.8810986319770695
            ],
            "pivot": [-6.695703837480391, 4.875000000000007, 4.205158843780348],
            "rotation": [
              -42.98907670370542, 65.1276783171143, -14.909920389584858
            ],
            "size": [4.499999999999995, 0.0, 5.500000000000002],
            "uv": {
              "up": {
                "texture": 2,
                "uv": [9, 11],
                "uv_size": [-9, -11]
              }
            }
          }
        ],
        "name": "leaf_4",
        "parent": "root",
        "pivot": [-8, -1, 8],
        "rotation": [0, 90, 0]
      },
      {
        "cubes": [
          {
            "origin": [-6.646446609406726, 7.75, 4.431980515339465],
            "pivot": [-5.396446609406726, 7.75, 5.931980515339465],
            "rotation": [
              167.49999929916342, 72.50000082468246, 179.99999926515267
            ],
            "size": [2.5, 0.0, 3.0],
            "uv": {
              "up": {
                "texture": 1,
                "uv": [5, 6],
                "uv_size": [-5, -6]
              }
            }
          },
          {
            "origin": [-5.088087845973531, 1.875, 2.6545528411457546],
            "pivot": [-2.83808784597353, 1.875, 5.404552841145755],
            "rotation": [
              -49.15609206332006, 67.3247753453211, -26.381034676993718
            ],
            "size": [4.5, 0.0, 5.5],
            "uv": {
              "up": {
                "texture": 2,
                "uv": [9, 11],
                "uv_size": [-9, -11]
              }
            }
          },
          {
            "origin": [-9.338087845973531, 3.875, 1.4045528411457546],
            "pivot": [-7.08808784597353, 3.875, 4.154552841145755],
            "rotation": [
              151.4803376355413, -21.63819646957157, -169.38073197828956
            ],
            "size": [4.5, 0.0, 5.5],
            "uv": {
              "up": {
                "texture": 2,
                "uv": [9, 11],
                "uv_size": [-9, -11]
              }
            }
          },
          {
            "origin": [-6.588087845973531, 4.875, -0.5954471588542454],
            "pivot": [-4.33808784597353, 4.875, 2.1545528411457546],
            "rotation": [
              163.65080153996905, 0.6286301196270034, 178.97728777600503
            ],
            "size": [4.5, 0.0, 5.5],
            "uv": {
              "up": {
                "texture": 2,
                "uv": [9, 11],
                "uv_size": [-9, -11]
              }
            }
          },
          {
            "origin": [-6.588087845973531, 0.875, -0.3454471588542454],
            "pivot": [-4.33808784597353, 0.875, 2.4045528411457546],
            "rotation": [
              149.40128614397736, -10.803551639575998, -173.67473784405902
            ],
            "size": [4.5, 0.0, 5.5],
            "uv": {
              "up": {
                "texture": 2,
                "uv": [9, 11],
                "uv_size": [-9, -11]
              }
            }
          }
        ],
        "name": "leaf_3",
        "parent": "root",
        "pivot": [-8, -1, 8],
        "rotation": [0, 0, 0]
      },
      {
        "cubes": [
          {
            "origin": [-8.56151011886782, 5.079629131445343, 8.266917005878371],
            "pivot": [-6.396446609406726, 0.25, 10.681980515339465],
            "rotation": [
              -10.546838899210972, 0.9762004016005328, 10.546838899210995
            ],
            "size": [2.4999999999999964, 0.0, 3.0],
            "uv": {
              "up": {
                "texture": 1,
                "uv": [5, 6],
                "uv_size": [-5, -6]
              }
            }
          },
          {
            "origin": [
              -6.896446609406724, 3.500000000000001, 7.931980515339464
            ],
            "pivot": [
              -5.646446609406723, 3.5000000000000004, 9.431980515339465
            ],
            "rotation": [
              -28.795904607596988, 80.70177471859756, -45.41553835862831
            ],
            "size": [2.5, 0.0, 3.000000000000001],
            "uv": {
              "up": {
                "texture": 1,
                "uv": [5, 6],
                "uv_size": [-5, -6]
              }
            }
          },
          {
            "origin": [
              -5.171869777935984, 1.8389026961586308, 6.906940648157055
            ],
            "pivot": [-3.08808784597353, 0.625, 9.904552841145755],
            "rotation": [
              -170.2086006853092, 69.74544646027427, -157.41171745046015
            ],
            "size": [4.500000000000001, 0.0, 5.500000000000004],
            "uv": {
              "up": {
                "texture": 2,
                "uv": [9, 11],
                "uv_size": [-9, -11]
              }
            }
          },
          {
            "origin": [
              -6.2565772992861435, 3.6407604572767593, 10.896373327281896
            ],
            "pivot": [
              -3.973333685678634, 3.875000000000002, 13.565585340680423
            ],
            "rotation": [
              -25.901742336771797, 13.689032441804537, -7.8663098829563936
            ],
            "size": [4.5, 0.0, 5.500000000000007],
            "uv": {
              "up": {
                "texture": 2,
                "uv": [9, 11],
                "uv_size": [-9, -11]
              }
            }
          },
          {
            "origin": [
              -7.546749760394012, 4.9242625541312695, 10.872344428660874
            ],
            "pivot": [
              -3.973333685678634, 3.875000000000002, 13.565585340680423
            ],
            "rotation": [
              -19.86760378546164, -28.407852289897516, -8.69525213374148
            ],
            "size": [4.5, 0.0, 5.500000000000007],
            "uv": {
              "up": {
                "texture": 2,
                "uv": [9, 11],
                "uv_size": [-9, -11]
              }
            }
          },
          {
            "origin": [
              -6.385271664587338, 7.629695037234829, 7.612317037048162
            ],
            "pivot": [
              -4.883580154300441, 7.625934503944454, 10.107326326212135
            ],
            "rotation": [
              -105.18060944644348, 82.26755905617047, -81.23076570673342
            ],
            "size": [4.5, 0.0, 5.500000000000006],
            "uv": {
              "up": {
                "texture": 2,
                "uv": [9, 11],
                "uv_size": [-9, -11]
              }
            }
          },
          {
            "origin": [
              -9.782284934951045, 2.7022050464712777, 8.783290863799747
            ],
            "pivot": [
              -6.978611836612444, 2.6259345039444533, 11.544644476387763
            ],
            "rotation": [
              -19.86760378546163, -28.407852289897516, -8.695252133741485
            ],
            "size": [4.500000000000001, 0.0, 5.500000000000007],
            "uv": {
              "up": {
                "texture": 2,
                "uv": [9, 11],
                "uv_size": [-9, -11]
              }
            }
          }
        ],
        "name": "leaf_2",
        "parent": "root",
        "pivot": [-8, 0, 8],
        "rotation": [0, -90, 0]
      },
      {
        "cubes": [
          {
            "origin": [-5.396446609406726, 7, 9.181980515339465],
            "pivot": [-4.146446609406726, 7, 10.681980515339465],
            "rotation": [
              71.09100974562182, 79.3487756151189, 81.95867784436442
            ],
            "size": [2.5, 0, 3.0],
            "uv": {
              "up": {
                "texture": 1,
                "uv": [5, 6],
                "uv_size": [-5, -6]
              }
            }
          },
          {
            "origin": [-7.896446609406726, 9, 8.931980515339465],
            "pivot": [-6.646446609406726, 9, 10.431980515339465],
            "rotation": [
              17.29152404572885, -8.995463405651531, -6.690617173586524
            ],
            "size": [2.5, 0, 3.0],
            "uv": {
              "up": {
                "texture": 1,
                "uv": [5, 6],
                "uv_size": [-5, -6]
              }
            }
          },
          {
            "origin": [-5.338087845973531, 1.375, 7.654552841145755],
            "pivot": [-3.08808784597353, 1.375, 10.404552841145755],
            "rotation": [
              -175.54735048065865, 79.72998747336345, -145.17997134512717
            ],
            "size": [4.5, 0.0, 5.5],
            "uv": {
              "up": {
                "texture": 2,
                "uv": [9, 11],
                "uv_size": [-9, -11]
              }
            }
          },
          {
            "origin": [-7.338087845973531, 3.875, 5.404552841145755],
            "pivot": [-5.08808784597353, 3.875, 8.154552841145755],
            "rotation": [
              158.8219834208291, 56.09164077208441, -169.48547214244243
            ],
            "size": [4.5, 0.0, 5.5],
            "uv": {
              "up": {
                "texture": 2,
                "uv": [9, 11],
                "uv_size": [-9, -11]
              }
            }
          },
          {
            "origin": [-4.588087845973531, 4.875, 8.654552841145755],
            "pivot": [-2.33808784597353, 4.875, 11.404552841145755],
            "rotation": [
              -111.50341094183626, 87.60817912470097, -102.2125746990739
            ],
            "size": [4.5, 0.0, 5.5],
            "uv": {
              "up": {
                "texture": 2,
                "uv": [9, 11],
                "uv_size": [-9, -11]
              }
            }
          },
          {
            "origin": [-9.588087845973531, 2.375, 8.154552841145755],
            "pivot": [-7.33808784597353, 2.375, 10.904552841145755],
            "rotation": [
              -32.71011340169823, -16.95575153762515, 9.150539053252718
            ],
            "size": [4.5, 0.0, 5.5],
            "uv": {
              "up": {
                "texture": 2,
                "uv": [9, 11],
                "uv_size": [-9, -11]
              }
            }
          },
          {
            "origin": [-9.088087845973531, 5.375, 8.904552841145755],
            "pivot": [-6.83808784597353, 5.375, 11.654552841145755],
            "rotation": [
              -20.210113401698436, -16.955751537625158, 9.150539053252722
            ],
            "size": [4.5, 0.0, 5.5],
            "uv": {
              "up": {
                "texture": 2,
                "uv": [9, 11],
                "uv_size": [-9, -11]
              }
            }
          },
          {
            "origin": [-6.588087845973531, 2.875, 11.154552841145755],
            "pivot": [-4.33808784597353, 2.875, 13.904552841145755],
            "rotation": [
              -29.588448626874758, 2.805393511860337, 8.760154669015314
            ],
            "size": [4.5, 0.0, 5.5],
            "uv": {
              "up": {
                "texture": 2,
                "uv": [9, 11],
                "uv_size": [-9, -11]
              }
            }
          }
        ],
        "name": "leaf_1",
        "parent": "root",
        "pivot": [-8, 0, 8],
        "rotation": [0, 0, 0]
      }
    ],
    "description": {
      "identifier": "ham:yam_stage_3",
      "textures": [
        "ham:yam_stage_3",
        "ham:yam_leaf_small",
        "ham:yam_leaf",
        "ham:yam_core"
      ],
      "textures_descriptions": [
        {
          "length": 16,
          "width": 16
        },
        {
          "length": 16,
          "width": 16
        },
        {
          "length": 16,
          "width": 16
        },
        {
          "length": 16,
          "width": 16
        }
      ],
      "use_ao": true
    }
  }
}
