{
  "parent": "pan",
  "sortnum": 12102,
  "icon": "textures/items/foods/simple/sausage.png",
  "title": "香肠",
  "pages": [
    {
      "type": "ham:panRecipePage",
      "recipeId": "ham:sausage",
      "content": "§8● §r§3类型: §5原材料\n§8● §r§3品质: §5●●§r\n§8● §r§3饥饿: §5●●§r"
    },
    {
      "subtitle": "烤熟",
      "type": "ham:grillRecipePage",
      "recipeId": "ham:sausage",
      "content": "§8● §r在烧烤架上烤熟"
    },
    {
      "subtitle": "蒸熟",
      "type": "ham:steamerRecipePage",
      "recipeId": "ham:sausage",
      "content": "8● §r在蒸笼架上蒸熟\n§8● §r需要消耗水，不如煎熟"
    }
  ]
}
